layerlearn/Flexible_Stacked_Classifier.py
layerlearn/Flexible_Stacked_Regressor.py
layerlearn/__init__.py
layerlearnyashw-0.1.0.dist-info/METADATA
layerlearnyashw-0.1.0.dist-info/WHEEL
layerlearnyashw-0.1.0.dist-info/licenses/LICENSE
layerlearnyashw-0.1.0.dist-info/RECORD
