Metadata-Version: 2.4
Name: layerlearnyashw
Version: 0.1.0
Summary: A simple library for flexible model stacking in scikit-learn.
Project-URL: Homepage, https://github.com/Mr-J12/newalgo
Author-email: Yashwant Singh Rawat <yashwantsinghrawat696@gmail.com>
License: MIT License
License-File: LICENSE
Classifier: Intended Audience :: Developers
Classifier: Operating System :: OS Independent
Classifier: Programming Language :: Python :: 3
Classifier: Topic :: Scientific/Engineering :: Artificial Intelligence
Requires-Python: >=3.8
Requires-Dist: numpy>=1.20.0
Requires-Dist: scikit-learn>=1.0.0
